c_formatter_42/__init__.py
c_formatter_42/__main__.py
c_formatter_42/run.py
c_formatter_42/data/.clang-format
c_formatter_42/data/__init__.py
c_formatter_42/data/clang-format-darwin
c_formatter_42/data/clang-format-linux
c_formatter_42/data/clang-format-win32.exe
c_formatter_42/formatters/__init__.py
c_formatter_42/formatters/align.py
c_formatter_42/formatters/clang_format.py
c_formatter_42/formatters/helper.py
c_formatter_42/formatters/hoist.py
c_formatter_42/formatters/line_breaker.py
c_formatter_42/formatters/misc.py
c_formatter_42/formatters/preprocessor_directive.py
c_formatter_42/formatters/return_type_single_tab.py
c_formatter_42-0.2.7.dist-info/LICENSE
c_formatter_42-0.2.7.dist-info/METADATA
c_formatter_42-0.2.7.dist-info/WHEEL
c_formatter_42-0.2.7.dist-info/entry_points.txt
c_formatter_42-0.2.7.dist-info/top_level.txt
c_formatter_42-0.2.7.dist-info/RECORD
