Metadata-Version: 2.1
Name: c_formatter_42
Version: 0.2.7
Summary: formatting tool complient with 42 school's norm
Home-page: https://github.com/dawnbeen/c_formatter_42
Project-URL: Tracker, https://github.com/dawnbeen/c_formatter_42/issues
Classifier: Programming Language :: Python :: 3.7
Classifier: Programming Language :: Python :: 3.8
Classifier: Programming Language :: Python :: 3.9
Classifier: Programming Language :: Python :: 3.10
Classifier: Programming Language :: Python :: 3.11
Classifier: Programming Language :: C
Classifier: Intended Audience :: Developers
Classifier: Environment :: Console
Classifier: Operating System :: Microsoft :: Windows
Classifier: Operating System :: MacOS
Classifier: Operating System :: POSIX :: Linux
Requires-Python: >=3.7
License-File: LICENSE
